{
  "timestamp": "2026-04-12T08:32:59Z",
  "diff_summary": {
    "files_changed": 2,
    "lines_added": 22,
    "lines_removed": 19,
    "files": [
      ".perception/quality-conscience.json",
      "src/pages/Dashboard.tsx"
    ]
  },
  "dimensions": {
    "completeness": {
      "score": 10.0,
      "issues": [],
      "checks_run": 5
    },
    "craftsmanship": {
      "score": 10.0,
      "issues": [],
      "checks_run": 8
    },
    "user_impact": {
      "score": 7.0,
      "issues": [
        "Changes 1 UI file(s) — directly visible to users",
        "Touches demo-relevant area(s): dashboard, schedule"
      ],
      "checks_run": 5
    },
    "pride": {
      "score": 10.0,
      "issues": [
        "Clean, focused commit with high completeness and craftsmanship"
      ],
      "checks_run": 4
    }
  },
  "verdict": "PASS",
  "average_score": 9.2,
  "scores": {
    "completeness": 10.0,
    "craftsmanship": 10.0,
    "user_impact": 7.0,
    "pride": 10.0
  },
  "improvement": ""
}